[{"header" : {"descriptor" : "Shield shape: The shield is", "dieSize" : 6, "rollsRequired" : 1}, "results" : ["Rectangular.", "Circular.", "Elliptical.", "Escutcheon.", "Square.", "Triangular."], "rollBehavior" : "REPEAT"}, {"header" : {"descriptor" : "Shield material: The shield is made of", "dieSize" : 6, "rollsRequired" : 1}, "results" : ["Animal hide stretched over a frame.", "Ash.", "Hickory.", "Oak.", "Bronze.", "Steel."], "rollBehavior" : "REPEAT"}, {"header" : {"descriptor" : "Shield feature: The shield has", "dieSize" : 6, "rollsRequired" : 1}, "results" : ["Reinforcing steel bands.", "Fur-lined leather straps.", "Sharp edges.", "Spikes.", "Gilding.", "Visible steel rivets."], "rollBehavior" : "REPEAT"}, {"header" : {"descriptor" : "Pattern: The shield is adorned with", "dieSize" : 6, "rollsRequired" : 1}, "results" : ["Horizontal stripes.", "Vertical stripes.", "Checker pattern.", "Two vertically divided fields.", "Two horizontally divided fields.", "Counterchanging quadrants."], "rollBehavior" : "REPEAT"}, {"header" : {"descriptor" : "Image: The shield is adorned with an image of a/an", "dieSize" : 6, "rollsRequired" : 1}, "results" : ["Heavenly phenomenon (5): 1. sun; 2. moon; 3. stars; 4. comet; 5. lightning; 6. rain clouds.", "Great beast (1): 1. kraken; 2. dragon; 3. lion; 4. wolf; 5. boar; 6. stag.", "Diminutive beast (3): 1. badger; 2. snake; 3. bat; 4. rabbit; 5. fox; 6. frog.", "Bird (1): 1. eagle; 2. owl; 3. vulture; 4. swan; 5. rooster; 6. sparrow.", "Symbol of war (3): 1. broadsword; 2. crossed swords; 3. crossed spears; 4. flames; 5. skull; 6. crow.", "Plant (6): 1. oak tree; 2. fir tree; 3. rose; 4. clover; 5. sunflower; 6. briar."], "rollBehavior" : "REPEAT"}, {"header" : {"descriptor" : "Paint color: The shield is painted", "dieSize" : 6, "rollsRequired" : 1}, "results" : ["Black.", "White.", "Red.", "Gold.", "Blue.", "Green."], "rollBehavior" : "REPEAT"}, {"header" : {"descriptor" : "Special protection: When properly activated, the shield provides extra protection against", "dieSize" : 6, "rollsRequired" : 1}, "results" : ["Acid damage.", "Cold damage.", "Fire damage.", "Necrotic damage.", "Lightning damage.", "Radiant damage."], "rollBehavior" : "REPEAT"}, {"header" : {"descriptor" : "Special property: The shield", "dieSize" : 6, "rollsRequired" : 1}, "results" : ["Stuns attackers who score a critical hit.", "Erupts with a burst of flame when hit.", "Creates magical camouflage.", "Doubles as a flotation device.", "Returns to the wielder\u2019s arm when thrown.", "Never breaks."], "rollBehavior" : "REPEAT"}, {"header" : {"descriptor" : "Activation: The shield\u2019s special protection or special property activates or amplifies", "dieSize" : 6, "rollsRequired" : 1}, "results" : ["Against a specific type of enemy (5): 1. dragons; 2. giants; 3. fiends; 4. aberrations; 5. elementals; 6. undead.", "When wielded by a member of a specific race (4): 1. high elf; 2. dwarf; 3. 4. goblinoid; 5. lizardfolk; 6. wood elf.", "In sunlight.", "In moonlight.", "In places touched by death.", "In places touched by faerie magic."], "rollBehavior" : "REPEAT"}, {"header" : {"descriptor" : "Creator: The shield was made by a/an", "dieSize" : 6, "rollsRequired" : 1}, "results" : ["Elvish mastercrafter.", "Dwarvish armorer.", "Young blacksmith.", "One-armed armorer.", "Devoted priest.", "Reclusive craftsman."], "rollBehavior" : "REPEAT"}, {"header" : {"descriptor" : "Past wielder: The shield\u2019s most famous wielder was a/an", "dieSize" : 6, "rollsRequired" : 1}, "results" : ["Dwarvish battlelord.", "Legendary elvish hero.", "Brutal outlaw.", "Zealous knight.", "Celebrated warpriest.", "Fearsome warlord."], "rollBehavior" : "REPEAT"}]